importers/__init__.py
importers/binance_us.py
importers/bitmart.py
importers/coinbase.py
importers/coinbasepro.py
importers/kraken.py
rp2_conv-1.26.21.dist-info/LICENSE
rp2_conv-1.26.21.dist-info/METADATA
rp2_conv-1.26.21.dist-info/WHEEL
rp2_conv-1.26.21.dist-info/top_level.txt
rp2_conv-1.26.21.dist-info/RECORD
